hardware/0v1/vhdl/kb_ctrl/kb_addr_decoder.vhdl
library IEEE;
use IEEE.std_logic_1164.all;

entity kb_addr_decoder is
  port (
   e    : in  std_logic;
   a    : in  std_logic_vector(1 downto 0);
   c    : out std_logic_vector(3 downto 0));
end entity kb_addr_decoder;

architecture rtl of kb_addr_decoder is
begin
  process (e, a)
  begin
    if e = '1' then 
      case a is 
        when "00" => c <= "0001";
        when "01" => c <= "0010";
        when "10" => c <= "0100";
        when "11" => c <= "1000";
        when others => c <= "0000";
      end case;
    else
      c <= "0000";
    end if;
  end process;
end architecture rtl;

hardware/0v1/vhdl/kb_ctrl/kb_addr_decoder_tb.vhdl
library IEEE;
use IEEE.std_logic_1164.all;

entity kb_addr_decoder_tb is
end entity kb_addr_decoder_tb;

architecture behav of kb_addr_decoder_tb is
  component kb_addr_decoder 
    port (
     e    : in  std_logic;
     a    : in  std_logic_vector(1 downto 0);
     c    : out std_logic_vector(3 downto 0));
  end component;
  for kb_addr_decoder_0: kb_addr_decoder use entity work.kb_addr_decoder;
  signal e : std_logic;
  signal a : std_logic_vector(1 downto 0);
  signal c : std_logic_vector(3 downto 0);
begin
  kb_addr_decoder_0: kb_addr_decoder port map (e => e, a => a, c => c);
  process 
    type pattern_type is record
     e : std_logic;
     a : std_logic_vector(1 downto 0);
     c : std_logic_vector(3 downto 0);
    end record;
    type pattern_array is array (natural range <>) of pattern_type; 
    constant patterns : pattern_array := (
      ('1', "00", "0001"),
      ('1', "01", "0010"),
      ('1', "10", "0100"),
      ('1', "11", "1000"),
      ('1', "X1", "0000"),
      ('1', "1X", "0000"),
      ('1', "XX", "0000"),

      ('0', "00", "0000"),
      ('0', "01", "0000"),
      ('0', "10", "0000"),
      ('0', "11", "0000"),
      ('0', "XX", "0000")
    );
  begin
    for i in patterns'range loop 
      e <= patterns(i).e;
      a <= patterns(i).a;
      wait for 1 ns;
      assert c = patterns(i).c 
        report "bad c value" severity error;
    end loop;
    assert false report "end of test" severity note;
    wait;
  end process;
  
end architecture behav;

hardware/0v1/vhdl/kb_ctrl/kb_addr_decoder_tb.vcd
$date
  Tue Dec 19 23:56:30 2023
$end
$version
  GHDL v0
$end
$timescale
  1 fs
$end
$scope module standard $end
$upscope $end
$scope module textio $end
$upscope $end
$scope module std_logic_1164 $end
$upscope $end
$scope module kb_addr_decoder_tb $end
$var reg 1 ! e $end
$var reg 2 " a[1:0] $end
$var reg 4 # c[3:0] $end
$scope module kb_addr_decoder_0 $end
$var reg 1 $ e $end
$var reg 2 % a[1:0] $end
$var reg 4 & c[3:0] $end
$upscope $end
$upscope $end
$enddefinitions $end
#0
1!
b00 "
b0001 #
1$
b00 %
b0001 &
#1000000
b01 "
b0010 #
b01 %
b0010 &
#2000000
b10 "
b0100 #
b10 %
b0100 &
#3000000
b11 "
b1000 #
b11 %
b1000 &
#4000000
bX1 "
b0000 #
bX1 %
b0000 &
#5000000
b1X "
b1X %
#6000000
bXX "
bXX %
#7000000
0!
b00 "
0$
b00 %
#8000000
b01 "
b01 %
#9000000
b10 "
b10 %
#10000000
b11 "
b11 %
#11000000
bXX "
bXX %
