hardware/0v1/vhdl/kb_ctrl/kb_addr_decoder.vhdl
library IEEE;
use IEEE.std_logic_1164.all;

entity kb_addr_decoder is
  port (
   e    : in  std_logic;
   a    : in  std_logic_vector(1 downto 0);
   c    : out std_logic_vector(3 downto 0));
end entity kb_addr_decoder;

architecture rtl of kb_addr_decoder is
begin
  process (e, a)
  begin
    if e = '1' then 
      case a is 
        when "00" => c <= "0001";
        when "01" => c <= "0010";
        when "10" => c <= "0100";
        when "11" => c <= "1000";
        when others => c <= "0000";
      end case;
    else
      c <= "0000";
    end if;
  end process;
end architecture rtl;

hardware/0v1/vhdl/kb_ctrl/kb_ctrl.vhdl
library IEEE;
use IEEE.std_logic_1164.all;
-- use IEEE.numeric_std.all;

entity kb_ctrl is 
  port (
    nce   : in  std_logic;
    noe   : in  std_logic;
    nwe   : in  std_logic;
    a     : in  std_logic_vector(1 downto 0);
    r     : in  std_logic_vector(3 downto 0);
    c     : out std_logic_vector(3 downto 0);
    d_out : out std_logic_vector(7 downto 0)
  );
end kb_ctrl;

architecture rtl of kb_ctrl is
  component kb_addr_decoder 
    port (
      e   : in  std_logic;
      a   : in  std_logic_vector(1 downto 0);
      c   : out std_logic_vector(3 downto 0));
  end component;
  signal intenral_enabled : std_logic;
begin
  intenral_enabled <= NOT (nce OR noe OR (NOT nwe)); 
  addr_decoder_unit: kb_addr_decoder port map (e => intenral_enabled, a => a, c => c);
  process (intenral_enabled, r)
  begin 
    if intenral_enabled = '1' then 
      d_out <= "0000" & r;
    else 
      d_out <= "ZZZZZZZZ";
    end if;
  end process;
end architecture rtl;

hardware/0v1/vhdl/kb_ctrl/kb_ctrl_tb.vhdl
library IEEE;
use IEEE.std_logic_1164.all;


entity kb_ctrl_tb is
end entity kb_ctrl_tb;

architecture behav of kb_ctrl_tb is
  component kb_ctrl 
    port (
      nce, noe, nwe  : in  std_logic;
      a              : in  std_logic_vector(1 downto 0);
      r              : in  std_logic_vector(3 downto 0);
      c              : out std_logic_vector(3 downto 0);
      d_out          : out std_logic_vector(7 downto 0)
    );
  end component;
  for kb_ctrl_0: kb_ctrl use entity work.kb_ctrl;
  signal nce, noe, nwe : std_logic;
  signal d_out  : std_logic_vector(7 downto 0);
  signal a      : std_logic_vector(1 downto 0);
  signal c,r    : std_logic_vector(3 downto 0);
begin
  kb_ctrl_0: kb_ctrl 
    port map (
      nce     => nce,
      noe     => noe,
      nwe     => nwe,
      d_out   => d_out,
      a       => a,
      r       => r,
      c       => c
    );
  process 
    type pattern_type is record 
      nce, noe, nwe  : std_logic;
      a              : std_logic_vector(1 downto 0);
      d_out          : std_logic_vector(7 downto 0);
    end record;
    type pattern_array is array (natural range <>) of pattern_type;
    constant patterns : pattern_array := ( 
      ('0', '0', '0', "00", "ZZZZZZZZ"),
      ('1', '0', '0', "00", "ZZZZZZZZ"),
      ('1', '0', '1', "00", "ZZZZZZZZ"),
      ('0', '1', '0', "00", "ZZZZZZZZ"),
      ('0', '1', '1', "00", "ZZZZZZZZ"),
      ('1', '1', '1', "00", "ZZZZZZZZ"),

      ('0', '0', '1', "00", "00000001"),
      ('0', '0', '1', "01", "00000010"),
      ('0', '0', '1', "10", "00000100"),
      ('0', '0', '1', "11", "00001000")
    );
  begin
    for i in patterns'range loop 
      nce <= patterns(i).nce;
      noe <= patterns(i).noe;
      nwe <= patterns(i).nwe;
      a <= patterns(i).a;
      wait for 500 ps;
      r <= c; -- loop back column to the row
      wait for 500 ps;
      assert d_out = patterns(i).d_out 
        report "bad d_out value in set: " & integer'image(i) severity error;
    end loop;
    assert false report "end of test" severity note;
    wait;
  end process;
end architecture behav;

hardware/0v1/vhdl/kb_ctrl/kb_ctrl.vcd
$date
  Tue Dec 19 23:56:30 2023
$end
$version
  GHDL v0
$end
$timescale
  1 fs
$end
$scope module standard $end
$upscope $end
$scope module textio $end
$upscope $end
$scope module std_logic_1164 $end
$upscope $end
$scope module kb_ctrl_tb $end
$var reg 1 ! nce $end
$var reg 1 " noe $end
$var reg 1 # nwe $end
$var reg 8 $ d_out[7:0] $end
$var reg 2 % a[1:0] $end
$var reg 4 & c[3:0] $end
$var reg 4 ' r[3:0] $end
$scope module kb_ctrl_0 $end
$var reg 1 ( nce $end
$var reg 1 ) noe $end
$var reg 1 * nwe $end
$var reg 2 + a[1:0] $end
$var reg 4 , r[3:0] $end
$var reg 4 - c[3:0] $end
$var reg 8 . d_out[7:0] $end
$var reg 1 / intenral_enabled $end
$scope module addr_decoder_unit $end
$var reg 1 0 e $end
$var reg 2 1 a[1:0] $end
$var reg 4 2 c[3:0] $end
$upscope $end
$upscope $end
$upscope $end
$enddefinitions $end
#0
0!
0"
0#
bZZZZZZZZ $
b00 %
b0000 &
bUUUU '
0(
0)
0*
b00 +
bUUUU ,
b0000 -
bZZZZZZZZ .
0/
00
b00 1
b0000 2
#500000
b0000 '
b0000 ,
#1000000
1!
1(
#1500000
#2000000
1#
1*
#2500000
#3000000
0!
1"
0#
0(
1)
0*
#3500000
#4000000
1#
1*
#4500000
#5000000
1!
1(
#5500000
#6000000
0!
0"
b00000000 $
b0001 &
0(
0)
b0001 -
b00000000 .
1/
10
b0001 2
#6500000
b00000001 $
b0001 '
b0001 ,
b00000001 .
#7000000
b01 %
b0010 &
b01 +
b0010 -
b01 1
b0010 2
#7500000
b00000010 $
b0010 '
b0010 ,
b00000010 .
#8000000
b10 %
b0100 &
b10 +
b0100 -
b10 1
b0100 2
#8500000
b00000100 $
b0100 '
b0100 ,
b00000100 .
#9000000
b11 %
b1000 &
b11 +
b1000 -
b11 1
b1000 2
#9500000
b00001000 $
b1000 '
b1000 ,
b00001000 .
