hardware/0v1/vhdl/ic_selector/clk_ctrl.vhdl
library IEEE;
use IEEE.std_logic_1164.all;
use IEEE.numeric_std.all;


entity clk_ctrl is
  port (
    master_clk : in std_logic;
    strech_selector : in std_logic_vector(1 downto 0);
    clk : out std_logic
  );
end entity clk_ctrl;

architecture rtl of clk_ctrl is
  signal s0_enabled : std_logic;
  signal s0_cnt : unsigned(3 downto 0);
begin
  s0_enabled <= strech_selector(0);
  sa :process(master_clk)
  begin
    if s0_enabled = '0' then
      clk <= master_clk;
      s0_cnt <= "0000";
    else 
      clk <= s0_cnt(2);
      s0_cnt <= s0_cnt + 1;
    end if;
  end process;
end architecture rtl;

hardware/0v1/vhdl/ic_selector/clk_ctrl_tb.vhdl
library IEEE;
use IEEE.std_logic_1164.all;

entity clk_ctrl_tb is
end entity clk_ctrl_tb;


architecture behav of clk_ctrl_tb is
  component clk_ctrl 
    port (
      master_clk : in std_logic; 
      strech_selector : in std_logic_vector (1 downto 0);
      clk : out std_logic
   );
  end component;


  signal master_clk : std_logic;
  signal strech_selector : std_logic_vector(1 downto 0);
  signal s_clk : std_logic;

  for dut: clk_ctrl use entity work.clk_ctrl;

  constant mclk_period : time := 1 ns;
begin
  dut: clk_ctrl port map(
    master_clk => master_clk,
    strech_selector => strech_selector,
    clk => s_clk);

  master_clk_process :process 
  begin 
    master_clk <= '0';
    wait for mclk_period/2;
    master_clk <= '1';
    wait for mclk_period/2;
  end process;

  test_process :process 
  begin 
    strech_selector <= "00";
    no_streach_test: for i in 0 to 10 loop 
      wait until master_clk = '0';
      wait for 1 ps;
      assert s_clk = '0' 
        report "bad s_clk no straching" severity error;
      wait until master_clk = '1';
      wait for 1 ps;
      assert s_clk = '1' 
        report "bad s_clk no straching" severity error;
    end loop;

    wait until master_clk = '0';
    strech_selector <= "01";
    wait for 5 ns;
    strech_selector <= "00";
    wait;

  end process;

end architecture behav;

hardware/0v1/vhdl/ic_selector/clk_ctrl_tb.vcd
$date
  Wed Jan  3 21:13:10 2024
$end
$version
  GHDL v0
$end
$timescale
  1 fs
$end
$scope module standard $end
$upscope $end
$scope module textio $end
$upscope $end
$scope module std_logic_1164 $end
$upscope $end
$scope module numeric_std $end
$upscope $end
$scope module clk_ctrl_tb $end
$var reg 1 ! master_clk $end
$var reg 2 " strech_selector[1:0] $end
$var reg 1 # s_clk $end
$scope module dut $end
$var reg 1 $ master_clk $end
$var reg 2 % strech_selector[1:0] $end
$var reg 1 & clk $end
$var reg 1 ' s0_enabled $end
$var reg 4 ( s0_cnt[3:0] $end
$upscope $end
$upscope $end
$enddefinitions $end
#0
0!
b00 "
X#
0$
b00 %
X&
0'
bXXXX (
#1000
#500000
1!
1#
1$
1&
b0000 (
#501000
#1000000
0!
0#
0$
0&
#1001000
#1500000
1!
1#
1$
1&
#1501000
#2000000
0!
0#
0$
0&
#2001000
#2500000
1!
1#
1$
1&
#2501000
#3000000
0!
0#
0$
0&
#3001000
#3500000
1!
1#
1$
1&
#3501000
#4000000
0!
0#
0$
0&
#4001000
#4500000
1!
1#
1$
1&
#4501000
#5000000
0!
0#
0$
0&
#5001000
#5500000
1!
1#
1$
1&
#5501000
#6000000
0!
0#
0$
0&
#6001000
#6500000
1!
1#
1$
1&
#6501000
#7000000
0!
0#
0$
0&
#7001000
#7500000
1!
1#
1$
1&
#7501000
#8000000
0!
0#
0$
0&
#8001000
#8500000
1!
1#
1$
1&
#8501000
#9000000
0!
0#
0$
0&
#9001000
#9500000
1!
1#
1$
1&
#9501000
#10000000
0!
0#
0$
0&
#10001000
#10500000
1!
1#
1$
1&
#10501000
#11000000
0!
b01 "
0#
0$
b01 %
0&
1'
#11500000
1!
1$
b0001 (
#12000000
0!
0$
b0010 (
#12500000
1!
1$
b0011 (
#13000000
0!
0$
b0100 (
#13500000
1!
1#
1$
1&
b0101 (
#14000000
0!
0$
b0110 (
#14500000
1!
1$
b0111 (
#15000000
0!
0$
b1000 (
#15500000
1!
0#
1$
0&
b1001 (
#16000000
0!
b00 "
0$
b00 %
0'
b1010 (
#16500000
1!
1#
1$
1&
b0000 (
