hardware/0v1/vhdl/ic_selector/ic_selector.vhdl
library IEEE;
use IEEE.std_logic_1164.all;
-- use IEEE.numeric_std.all;

entity ic_selector is
  port (
    clk    : in std_logic;
    rw     : in std_logic;
    a      : in std_logic_vector(15 downto 13);
    nce_rom : out std_logic; 
    nce_ram : out std_logic; 
    nce_key : out std_logic;
    e_lcd  : out std_logic;
    nwe    : out std_logic;
    noe    : out std_logic
  );
end entity ic_selector;

architecture rtl of ic_selector is
  
begin
  nce_rom <= not (a(15) and a(14) and a(13));
  nce_ram <= not (not a(15) and not a(14) and not a(13));
  nce_key <= not (a(15) and a(14) and not a(13));
  e_lcd <= (a(15) and not a(14) and not a(13)) and clk;
  
  nwe <= not clk or rw;
  noe <= not (rw and clk);

end architecture rtl;

hardware/0v1/vhdl/ic_selector/ic_selector_tb.vhdl
library IEEE;
use IEEE.std_logic_1164.all;
-- use IEEE.numeric_std.all;

entity ic_selector_tb is
end entity ic_selector_tb;


architecture behav of ic_selector_tb is
  component ic_selector 
    port (
      clk    : in std_logic;
      rw     : in std_logic;
      a      : in std_logic_vector(15 downto 13);
      nce_rom : out std_logic; 
      nce_ram : out std_logic; 
      nce_key : out std_logic;
      e_lcd  : out std_logic;
      nwe    : out std_logic;
      noe    : out std_logic
    );
  end component;

  signal clk     : std_logic;
  signal rw      : std_logic;
  signal a       : std_logic_vector(15 downto 13);
  signal nce_rom : std_logic; 
  signal nce_ram : std_logic; 
  signal nce_key : std_logic;
  signal e_lcd   : std_logic;
  signal nwe     : std_logic;
  signal noe     : std_logic;

  for ic_selector_0: ic_selector use entity work.ic_selector;
begin
  ic_selector_0: ic_selector port map(
    clk => clk, rw => rw, a => a, 
    nce_rom => nce_rom, nce_ram => nce_ram, 
    nce_key => nce_key, e_lcd => e_lcd, 
    nwe => nwe, noe => noe);

  process 
    type pattern_type is record
       clk     : std_logic;
       rw      : std_logic;
       a       : std_logic_vector(15 downto 13);
       nce_rom : std_logic; 
       nce_ram : std_logic; 
       nce_key : std_logic;
       e_lcd   : std_logic;
       nwe     : std_logic;
       noe     : std_logic;
    end record;
    type pattern_array is array (natural range <>) of pattern_type; 
    constant patterns : pattern_array := (
      -- clk low, write
      ('0', '0', "000", '1', '0', '1', '0', '1', '1'),
      ('0', '0', "001", '1', '1', '1', '0', '1', '1'),
      ('0', '0', "010", '1', '1', '1', '0', '1', '1'),
      ('0', '0', "011", '1', '1', '1', '0', '1', '1'),
      ('0', '0', "100", '1', '1', '1', '0', '1', '1'),
      ('0', '0', "101", '1', '1', '1', '0', '1', '1'),
      ('0', '0', "110", '1', '1', '0', '0', '1', '1'),
      ('0', '0', "111", '0', '1', '1', '0', '1', '1'),

      -- clk low, read
      ('0', '1', "000", '1', '0', '1', '0', '1', '1'),
      ('0', '1', "001", '1', '1', '1', '0', '1', '1'),
      ('0', '1', "010", '1', '1', '1', '0', '1', '1'),
      ('0', '1', "011", '1', '1', '1', '0', '1', '1'),
      ('0', '1', "100", '1', '1', '1', '0', '1', '1'),
      ('0', '1', "101", '1', '1', '1', '0', '1', '1'),
      ('0', '1', "110", '1', '1', '0', '0', '1', '1'),
      ('0', '1', "111", '0', '1', '1', '0', '1', '1'),

      -- clk high, write 
      ('1', '0', "000", '1', '0', '1', '0', '0', '1'),
      ('1', '0', "001", '1', '1', '1', '0', '0', '1'),
      ('1', '0', "010", '1', '1', '1', '0', '0', '1'),
      ('1', '0', "011", '1', '1', '1', '0', '0', '1'),
      ('1', '0', "100", '1', '1', '1', '1', '0', '1'),
      ('1', '0', "101", '1', '1', '1', '0', '0', '1'),
      ('1', '0', "110", '1', '1', '0', '0', '0', '1'),
      ('1', '0', "111", '0', '1', '1', '0', '0', '1'),

      -- clk high, read 
      ('1', '1', "000", '1', '0', '1', '0', '1', '0'),
      ('1', '1', "001", '1', '1', '1', '0', '1', '0'),
      ('1', '1', "010", '1', '1', '1', '0', '1', '0'),
      ('1', '1', "011", '1', '1', '1', '0', '1', '0'),
      ('1', '1', "100", '1', '1', '1', '1', '1', '0'),
      ('1', '1', "101", '1', '1', '1', '0', '1', '0'),
      ('1', '1', "110", '1', '1', '0', '0', '1', '0'),
      ('1', '1', "111", '0', '1', '1', '0', '1', '0')
    );
  begin
    for i in patterns'range loop
      -- report "test:" 
      --   & " rw: " & std_logic'image(patterns(i).rw)
      --   & " clk: " & std_logic'image(patterns(i).clk)
      --   & " a: " & std_logic'image(patterns(i).a(15))
      --     & std_logic'image(patterns(i).a(14))
      --     & std_logic'image(patterns(i).a(13));

      clk <= patterns(i).clk;
      rw <= patterns(i).rw;
      a <= patterns(i).a;
      wait for 1 ns;

      assert nce_rom = patterns(i).nce_rom 
        report "bad nce_rom value: " & std_logic'image(nce_rom) severity error;
      assert nce_ram = patterns(i).nce_ram 
        report "bad nce_ram value" & std_logic'image(nce_ram) severity error;
      assert nce_key = patterns(i).nce_key 
        report "bad nce_key value" & std_logic'image(nce_key) severity error;
      assert e_lcd = patterns(i).e_lcd 
        report "bad e_lcd value" & std_logic'image(e_lcd) severity error;
      assert nwe = patterns(i).nwe 
        report "bad nwe value" & std_logic'image(nwe) severity error;
      assert noe = patterns(i).noe 
        report "bad noe value" & std_logic'image(noe) severity error;
    end loop;

    report "end of test" severity note;
    wait;
  end process;
end architecture behav;

hardware/0v1/vhdl/ic_selector/ic_selector_tb.vcd
$date
  Thu Dec 14 13:59:38 2023
$end
$version
  GHDL v0
$end
$timescale
  1 fs
$end
$scope module standard $end
$upscope $end
$scope module textio $end
$upscope $end
$scope module std_logic_1164 $end
$upscope $end
$scope module ic_selector_tb $end
$var reg 1 ! clk $end
$var reg 1 " rw $end
$var reg 3 # a[15:13] $end
$var reg 1 $ nce_rom $end
$var reg 1 % nce_ram $end
$var reg 1 & nce_key $end
$var reg 1 ' e_lcd $end
$var reg 1 ( nwe $end
$var reg 1 ) noe $end
$scope module ic_selector_0 $end
$var reg 1 * clk $end
$var reg 1 + rw $end
$var reg 3 , a[15:13] $end
$var reg 1 - nce_rom $end
$var reg 1 . nce_ram $end
$var reg 1 / nce_key $end
$var reg 1 0 e_lcd $end
$var reg 1 1 nwe $end
$var reg 1 2 noe $end
$upscope $end
$upscope $end
$enddefinitions $end
#0
0!
0"
b000 #
1$
0%
1&
0'
1(
1)
0*
0+
b000 ,
1-
0.
1/
00
11
12
#1000000
b001 #
1%
b001 ,
1.
#2000000
b010 #
b010 ,
#3000000
b011 #
b011 ,
#4000000
b100 #
b100 ,
#5000000
b101 #
b101 ,
#6000000
b110 #
0&
b110 ,
0/
#7000000
b111 #
0$
1&
b111 ,
0-
1/
#8000000
1"
b000 #
1$
0%
1+
b000 ,
1-
0.
#9000000
b001 #
1%
b001 ,
1.
#10000000
b010 #
b010 ,
#11000000
b011 #
b011 ,
#12000000
b100 #
b100 ,
#13000000
b101 #
b101 ,
#14000000
b110 #
0&
b110 ,
0/
#15000000
b111 #
0$
1&
b111 ,
0-
1/
#16000000
1!
0"
b000 #
1$
0%
0(
1*
0+
b000 ,
1-
0.
01
#17000000
b001 #
1%
b001 ,
1.
#18000000
b010 #
b010 ,
#19000000
b011 #
b011 ,
#20000000
b100 #
1'
b100 ,
10
#21000000
b101 #
0'
b101 ,
00
#22000000
b110 #
0&
b110 ,
0/
#23000000
b111 #
0$
1&
b111 ,
0-
1/
#24000000
1"
b000 #
1$
0%
1(
0)
1+
b000 ,
1-
0.
11
02
#25000000
b001 #
1%
b001 ,
1.
#26000000
b010 #
b010 ,
#27000000
b011 #
b011 ,
#28000000
b100 #
1'
b100 ,
10
#29000000
b101 #
0'
b101 ,
00
#30000000
b110 #
0&
b110 ,
0/
#31000000
b111 #
0$
1&
b111 ,
0-
1/
