hardware/0v2/vhdl/ic_selector.vhdl
library IEEE;
use IEEE.std_logic_1164.all;
-- use IEEE.numeric_std.all;

entity ic_selector is
  port (
    clk        : in std_logic;
    rw         : in std_logic;
    a          : in std_logic_vector(15 downto 13);
    ce_rom_b   : out std_logic; 
    ce_ram_b   : out std_logic; 
    ce1_uart   : out std_logic; 
    ce2_uart_b : out std_logic; 
    we_b       : out std_logic;
    oe_b       : out std_logic
  );

end entity ic_selector;

architecture rtl of ic_selector is
  signal i_ce_uart : std_logic;
begin
  ce_ram_b <= a(15);
  ce_rom_b <= not(a(15) and a(14) and a(13));
  i_ce_uart <= a(15) and a(14) and not a(13);
  ce1_uart <= i_ce_uart; 
  ce2_uart_b <= not i_ce_uart;
  
  we_b <= not clk or rw;
  oe_b <= not (rw and clk);
end architecture rtl;

hardware/0v2/vhdl/ic_selector_tb.vhdl
library IEEE;
use IEEE.std_logic_1164.all;
-- use IEEE.numeric_std.all;

entity ic_selector_tb is
end entity ic_selector_tb;


architecture behav of ic_selector_tb is
  component ic_selector 
    port (
      clk        : in std_logic;
      rw         : in std_logic;
      a          : in std_logic_vector(15 downto 13);
      ce_rom_b   : out std_logic; 
      ce_ram_b   : out std_logic; 
      ce1_uart   : out std_logic; 
      ce2_uart_b : out std_logic; 
      we_b       : out std_logic;
      oe_b       : out std_logic
    );
  end component;

  signal clk        : std_logic;
  signal rw         : std_logic;
  signal a          : std_logic_vector(15 downto 13);
  signal ce_rom_b   : std_logic; 
  signal ce_ram_b   : std_logic; 
  signal ce1_uart   : std_logic; 
  signal ce2_uart_b : std_logic; 
  signal we_b       : std_logic;
  signal oe_b       : std_logic;

  for ic_selector_0: ic_selector use entity work.ic_selector;
begin
  ic_selector_0: ic_selector port map(
    clk => clk, rw => rw, a => a, 
    ce_rom_b => ce_rom_b, ce_ram_b => ce_ram_b, 
    ce1_uart => ce1_uart, ce2_uart_b => ce2_uart_b,
    we_b => we_b, oe_b => oe_b);

  process 
    type pattern_type is record
       clk        : std_logic;
       rw         : std_logic;
       a          : std_logic_vector(15 downto 13);
       ce_rom_b   : std_logic; 
       ce_ram_b   : std_logic; 
       ce1_uart   : std_logic; 
       ce2_uart_b : std_logic; 
       we_b       : std_logic;
       oe_b       : std_logic;
    end record;
    type pattern_array is array (natural range <>) of pattern_type; 
    constant patterns : pattern_array := (
      -- clk low, write
      ('0', '0', "000", '1', '0', '0', '1', '1', '1'),
      ('0', '0', "001", '1', '0', '0', '1', '1', '1'),
      ('0', '0', "010", '1', '0', '0', '1', '1', '1'),
      ('0', '0', "011", '1', '0', '0', '1', '1', '1'),
      ('0', '0', "100", '1', '1', '0', '1', '1', '1'),
      ('0', '0', "101", '1', '1', '0', '1', '1', '1'),
      ('0', '0', "110", '1', '1', '1', '0', '1', '1'),
      ('0', '0', "111", '0', '1', '0', '1', '1', '1'),

      -- clk low, read
      ('0', '1', "000", '1', '0', '0', '1', '1', '1'),
      ('0', '1', "001", '1', '0', '0', '1', '1', '1'),
      ('0', '1', "010", '1', '0', '0', '1', '1', '1'),
      ('0', '1', "011", '1', '0', '0', '1', '1', '1'),
      ('0', '1', "100", '1', '1', '0', '1', '1', '1'),
      ('0', '1', "101", '1', '1', '0', '1', '1', '1'),
      ('0', '1', "110", '1', '1', '1', '0', '1', '1'),
      ('0', '1', "111", '0', '1', '0', '1', '1', '1'),

      -- clk high, read
      ('1', '1', "000", '1', '0', '0', '1', '1', '0'),
      ('1', '1', "001", '1', '0', '0', '1', '1', '0'),
      ('1', '1', "010", '1', '0', '0', '1', '1', '0'),
      ('1', '1', "011", '1', '0', '0', '1', '1', '0'),
      ('1', '1', "100", '1', '1', '0', '1', '1', '0'),
      ('1', '1', "101", '1', '1', '0', '1', '1', '0'),
      ('1', '1', "110", '1', '1', '1', '0', '1', '0'),
      ('1', '1', "111", '0', '1', '0', '1', '1', '0'),

      -- clk high, write
      ('1', '0', "000", '1', '0', '0', '1', '0', '1'),
      ('1', '0', "001", '1', '0', '0', '1', '0', '1'),
      ('1', '0', "010", '1', '0', '0', '1', '0', '1'),
      ('1', '0', "011", '1', '0', '0', '1', '0', '1'),
      ('1', '0', "100", '1', '1', '0', '1', '0', '1'),
      ('1', '0', "101", '1', '1', '0', '1', '0', '1'),
      ('1', '0', "110", '1', '1', '1', '0', '0', '1'),
      ('1', '0', "111", '0', '1', '0', '1', '0', '1')
    );
  begin
    for i in patterns'range loop
      -- report "test:" 
      --   & " rw: " & std_logic'image(patterns(i).rw)
      --   & " clk: " & std_logic'image(patterns(i).clk)
      --   & " a: " & std_logic'image(patterns(i).a(15))
      --     & std_logic'image(patterns(i).a(14))
      --     & std_logic'image(patterns(i).a(13));

      clk <= patterns(i).clk;
      rw <= patterns(i).rw;
      a <= patterns(i).a;
      wait for 1 ns;

      assert ce_rom_b = patterns(i).ce_rom_b
        report "bad ce_rom_b value: " & std_logic'image(ce_rom_b) severity error;
      assert ce_ram_b = patterns(i).ce_ram_b
        report "bad ce_ram_b value" & std_logic'image(ce_ram_b) severity error;
      assert ce1_uart = patterns(i).ce1_uart 
        report "bad ce1_uart value" & std_logic'image(ce1_uart) severity error;
      assert ce2_uart_b = patterns(i).ce2_uart_b
        report "bad ce2_uart_b value" & std_logic'image(ce2_uart_b) severity error;
      assert we_b = patterns(i).we_b 
        report "bad we_b value" & std_logic'image(we_b) severity error;
      assert oe_b = patterns(i).oe_b
        report "bad oe_b value" & std_logic'image(oe_b) severity error;
    end loop;

    report "end of test" severity note;
    wait;
  end process;
end architecture behav;

hardware/0v2/vhdl/ic_selector_tb.vcd
$date
  Sat Jan  6 11:13:52 2024
$end
$version
  GHDL v0
$end
$timescale
  1 fs
$end
$scope module standard $end
$upscope $end
$scope module textio $end
$upscope $end
$scope module std_logic_1164 $end
$upscope $end
$scope module ic_selector_tb $end
$var reg 1 ! clk $end
$var reg 1 " rw $end
$var reg 3 # a[15:13] $end
$var reg 1 $ ce_rom_b $end
$var reg 1 % ce_ram_b $end
$var reg 1 & ce1_uart $end
$var reg 1 ' ce2_uart_b $end
$var reg 1 ( we_b $end
$var reg 1 ) oe_b $end
$scope module ic_selector_0 $end
$var reg 1 * clk $end
$var reg 1 + rw $end
$var reg 3 , a[15:13] $end
$var reg 1 - ce_rom_b $end
$var reg 1 . ce_ram_b $end
$var reg 1 / ce1_uart $end
$var reg 1 0 ce2_uart_b $end
$var reg 1 1 we_b $end
$var reg 1 2 oe_b $end
$var reg 1 3 i_ce_uart $end
$upscope $end
$upscope $end
$enddefinitions $end
#0
0!
0"
b000 #
1$
0%
0&
1'
1(
1)
0*
0+
b000 ,
1-
0.
0/
10
11
12
03
#1000000
b001 #
b001 ,
#2000000
b010 #
b010 ,
#3000000
b011 #
b011 ,
#4000000
b100 #
1%
b100 ,
1.
#5000000
b101 #
b101 ,
#6000000
b110 #
1&
0'
b110 ,
1/
00
13
#7000000
b111 #
0$
0&
1'
b111 ,
0-
0/
10
03
#8000000
1"
b000 #
1$
0%
1+
b000 ,
1-
0.
#9000000
b001 #
b001 ,
#10000000
b010 #
b010 ,
#11000000
b011 #
b011 ,
#12000000
b100 #
1%
b100 ,
1.
#13000000
b101 #
b101 ,
#14000000
b110 #
1&
0'
b110 ,
1/
00
13
#15000000
b111 #
0$
0&
1'
b111 ,
0-
0/
10
03
#16000000
1!
b000 #
1$
0%
0)
1*
b000 ,
1-
0.
02
#17000000
b001 #
b001 ,
#18000000
b010 #
b010 ,
#19000000
b011 #
b011 ,
#20000000
b100 #
1%
b100 ,
1.
#21000000
b101 #
b101 ,
#22000000
b110 #
1&
0'
b110 ,
1/
00
13
#23000000
b111 #
0$
0&
1'
b111 ,
0-
0/
10
03
#24000000
0"
b000 #
1$
0%
0(
1)
0+
b000 ,
1-
0.
01
12
#25000000
b001 #
b001 ,
#26000000
b010 #
b010 ,
#27000000
b011 #
b011 ,
#28000000
b100 #
1%
b100 ,
1.
#29000000
b101 #
b101 ,
#30000000
b110 #
1&
0'
b110 ,
1/
00
13
#31000000
b111 #
0$
0&
1'
b111 ,
0-
0/
10
03
