hardware/0v2/verilog/sprite_render.v
module dma(
  input wire clk,

  output wire [14:0] s_addr,
  inout wire [7:0] s_data,
  output wire s_re,
  output wire s_we,

  input wire [8:0] line_n,
  input wire off_src_line,

  output wire [9:0] r_addr,
  output wire r_we,

  input wire i_clk,
  input wire [1:0] i_addr,
  input wire [7:0] i_data,
  input wire i_we,
  input wire i_cs,
  output wire i_wait
);

localparam  ST_READ_Y = 3'h0,
            ST_READ_X = 3'h1,
            ST_READ_C = 3'h2,
            ST_READ_I = 3'h3,
            ST_WRITE = 3'h4;

reg [14:0] _i_addr;

reg [2:0] _state;
reg [5:0] _spr_cnt;
reg [31:0] _spr_reg; 

reg [2:0] _cpy_cnt;
reg _last_rst;

wire [7:0] _rnd_line;
wire [7:0] _y_diff;
wire [8:0] _spr_w_addr;
wire _write_state; 
wire _valid_pixel;
wire _line_reset;

assign _line_reset = line_n[0];
assign _rnd_line = line_n[8:1];
assign _y_diff = _rnd_line - _spr_reg[7:0];
assign _write_state = _state == ST_WRITE ? 1'h1 : 1'h0 ;
assign _valid_pixel = s_data == 8'h00 ? 1'h0 : 1'h1; // can be handled externally

assign s_addr = off_src_line ? _i_addr : (_write_state ? { _spr_reg[31:23], _y_diff[2:0], _cpy_cnt[2:0]} : {7'h0, _spr_cnt, _state[1:0]});
assign _spr_w_addr = _spr_reg[16:8] + {6'h0, _cpy_cnt};
assign r_addr = {~line_n[1], _spr_w_addr}; // line_n[1] can be wired externally
assign r_we = _write_state & clk & _valid_pixel ? 1'h1 : 1'h0; //todo: inverted signal ? 
assign i_wait = i_cs && i_addr == 2'h3 && !off_src_line;

assign s_data = off_src_line ? i_data : 8'bz;
assign s_re = !off_src_line; // can be probably removed and replaces by external wire
assign s_we = off_src_line && i_cs && i_we && i_addr == 2'h3;

// note: grey zone....
initial begin 
  _state = 3'b111;
  _spr_cnt = 6'h3f;
  _spr_reg = 32'h0;
  _cpy_cnt = 3'h0;
  _last_rst = 1'h0;
end

always @ (posedge clk) begin 
  case (_state) 
    ST_READ_Y: _spr_reg[7:0] = s_data;
    ST_READ_X: _spr_reg[15:8] = s_data;
    ST_READ_C: _spr_reg[23:16] = s_data;
    ST_READ_I: _spr_reg[31:24] = s_data;
    ST_WRITE: begin 
    end
    default: begin end
  endcase
end

always @ (negedge clk) begin 
  if(_last_rst != _line_reset) begin 
    if(~_line_reset) begin 
      _state = 0;
      _cpy_cnt = 0; 
      _spr_cnt = 0;
    end
    _last_rst = _line_reset;
  end else if(_y_diff > 8'h7) begin 
      _cpy_cnt = 0; 
      _state = 0;
      _spr_cnt = _spr_cnt + 1'h1;
  end else if(_write_state) begin 
    if(_cpy_cnt == 3'h7) begin 
      _cpy_cnt = 0;
      _state = 0;
      _spr_cnt = _spr_cnt + 1'h1;
    end else begin 
      _cpy_cnt = _cpy_cnt + 1'h1;
    end
  end else begin
    _state = _state + 1'h1;
  end
end

always @ (posedge i_clk) begin 
  if(i_cs && i_we && off_src_line) begin
    case (i_addr)
      2'h0: _i_addr[7:0] = i_data;
      2'h1: _i_addr[14:8] = i_data[6:0];
      default: begin end
    endcase 
  end
end
endmodule

hardware/0v2/verilog/sprite_render_tb.v
`timescale 1ns / 1ns
`include "sprite_render.v"

module sprite_ram(
  input wire s_re,
  input wire [14:0] s_addr,
  inout wire [7:0] s_data
);

reg [7:0] mem [0:16383];
assign s_data = s_re ? mem[s_addr] : 8'hz;

initial begin 
  $readmemh("sprite_ram.mem", mem);
end
endmodule

module sprite_render_tb();
reg clk;
reg [8:0] line_n;

reg i_clk;
reg [7:0] i_data;
reg [1:0] i_addr;
reg i_we;
reg i_cs;

wire s_re;
wire [14:0] s_addr;
wire [9:0] r_addr;
wire r_we;
wire [7:0] s_data;

sprite_ram spr_ram(
  .s_addr(s_addr),
  .s_data(s_data),
  .s_re(s_re)
);

dma dut(
  .clk(clk),
  .s_addr(s_addr),
  .s_data(s_data),
  .s_re(s_re),
  .line_n(line_n),
  .r_addr(r_addr),
  .r_we(r_we),
  .i_clk(i_clk),
  .i_data(i_data),
  .i_addr(i_addr),
  .i_we(i_we),
  .i_cs(i_cs)
);


parameter T_CLK2 = 10;

initial begin 
  $dumpfile("./out/sprite_render_tb.vcd");
  $dumpvars(0, sprite_render_tb);

  i_clk = 0;
  i_data = 8'h00;
  i_addr = 2'h0;
  i_we = 0;
  i_cs = 0;

  line_n = 9'h14;
  clk = 0;
  for (integer i = 0; i < 15; i = i + 1) begin 
    #T_CLK2 clk = 0; #T_CLK2 clk = 1;
  end

  line_n = 9'h15;
  for (integer i = 0; i < 10; i = i + 1) begin 
    #T_CLK2 clk = 0; #T_CLK2 clk = 1;
  end

  line_n = 9'h16;
  for (integer i = 0; i < 15; i = i + 1) begin 
    #T_CLK2 clk = 0; #T_CLK2 clk = 1;
  end

  line_n = 9'h17;
  for (integer i = 0; i < 10; i = i + 1) begin 
    #T_CLK2 clk = 0; #T_CLK2 clk = 1;
  end


  line_n = 9'h14;
  clk = 0;
  for (integer i = 0; i < 5; i = i + 1) begin 
    #T_CLK2 clk = 0; #T_CLK2 clk = 1;
  end

end

endmodule

hardware/0v2/verilog/out/sprite_render_tb.vcd
$date
	Sat Jun 22 22:34:05 2024
$end
$version
	Icarus Verilog
$end
$timescale
	1ns
$end
$scope module sprite_render_tb $end
$var wire 8 ! s_data [7:0] $end
$var wire 1 " s_re $end
$var wire 15 # s_addr [14:0] $end
$var wire 1 $ r_we $end
$var wire 10 % r_addr [9:0] $end
$var reg 1 & clk $end
$var reg 2 ' i_addr [1:0] $end
$var reg 1 ( i_clk $end
$var reg 1 ) i_cs $end
$var reg 8 * i_data [7:0] $end
$var reg 1 + i_we $end
$var reg 9 , line_n [8:0] $end
$scope module dut $end
$var wire 1 & clk $end
$var wire 2 - i_addr [1:0] $end
$var wire 1 ( i_clk $end
$var wire 1 ) i_cs $end
$var wire 8 . i_data [7:0] $end
$var wire 1 / i_wait $end
$var wire 1 + i_we $end
$var wire 9 0 line_n [8:0] $end
$var wire 1 1 off_src_line $end
$var wire 8 2 s_data [7:0] $end
$var wire 1 3 s_we $end
$var wire 1 " s_re $end
$var wire 15 4 s_addr [14:0] $end
$var wire 1 $ r_we $end
$var wire 10 5 r_addr [9:0] $end
$var wire 8 6 _y_diff [7:0] $end
$var wire 1 7 _write_state $end
$var wire 1 8 _valid_pixel $end
$var wire 9 9 _spr_w_addr [8:0] $end
$var wire 8 : _rnd_line [7:0] $end
$var wire 1 ; _line_reset $end
$var reg 3 < _cpy_cnt [2:0] $end
$var reg 15 = _i_addr [14:0] $end
$var reg 1 > _last_rst $end
$var reg 6 ? _spr_cnt [5:0] $end
$var reg 32 @ _spr_reg [31:0] $end
$var reg 3 A _state [2:0] $end
$upscope $end
$scope module spr_ram $end
$var wire 15 B s_addr [14:0] $end
$var wire 8 C s_data [7:0] $end
$var wire 1 " s_re $end
$upscope $end
$scope begin $ivl_for_loop0 $end
$var integer 32 D i [31:0] $end
$upscope $end
$scope begin $ivl_for_loop1 $end
$var integer 32 E i [31:0] $end
$upscope $end
$scope begin $ivl_for_loop2 $end
$var integer 32 F i [31:0] $end
$upscope $end
$scope begin $ivl_for_loop3 $end
$var integer 32 G i [31:0] $end
$upscope $end
$scope begin $ivl_for_loop4 $end
$var integer 32 H i [31:0] $end
$upscope $end
$upscope $end
$enddefinitions $end
#0
$dumpvars
bx H
bx G
bx F
bx E
b0 D
bx C
bx B
b0 A
b0 @
b0 ?
0>
bx =
b0 <
0;
b1010 :
b0 9
x8
07
b1010 6
b1000000000 5
bx 4
03
bx 2
z1
b10100 0
0/
b0 .
b0 -
b10100 ,
0+
b0 *
0)
0(
b0 '
0&
b1000000000 %
0$
bx #
x"
bx !
$end
#20
bx 6
b0xxxxxxxx @
b1 D
1&
#30
b1 A
0&
#40
b1xxxxxxxxx %
b1xxxxxxxxx 5
bx 9
b0xxxxxxxxxxxxxxxx @
b10 D
1&
#50
b10 A
0&
#60
b0xxxxxxxxxxxxxxxxxxxxxxxx @
b11 D
1&
#70
b11 A
0&
#80
bx @
b100 D
1&
#90
17
b100 A
0&
#100
x$
b101 D
1&
#110
0$
b1 <
0&
#120
x$
b110 D
1&
#130
0$
b10 <
0&
#140
x$
b111 D
1&
#150
0$
b11 <
0&
#160
x$
b1000 D
1&
#170
0$
b100 <
0&
#180
x$
b1001 D
1&
#190
0$
b101 <
0&
#200
x$
b1010 D
1&
#210
0$
b110 <
0&
#220
x$
b1011 D
1&
#230
0$
b111 <
0&
#240
x$
b1100 D
1&
#250
0$
07
b1 ?
b0 A
b0 <
0&
#260
b1101 D
1&
#270
b1 A
0&
#280
b1110 D
1&
#290
b10 A
0&
#300
1;
b0 E
b10101 ,
b10101 0
b1111 D
1&
#310
1>
0&
#320
b1 E
1&
#330
b11 A
0&
#340
b10 E
1&
#350
17
b100 A
0&
#360
x$
b11 E
1&
#370
0$
b1 <
0&
#380
x$
b100 E
1&
#390
0$
b10 <
0&
#400
x$
b101 E
1&
#410
0$
b11 <
0&
#420
x$
b110 E
1&
#430
0$
b100 <
0&
#440
x$
b111 E
1&
#450
0$
b101 <
0&
#460
x$
b1000 E
1&
#470
0$
b110 <
0&
#480
x$
b1001 E
1&
#490
0$
b111 <
0&
#500
x$
b0xxxxxxxxx %
b0xxxxxxxxx 5
0;
b1011 :
b0 F
b10110 ,
b10110 0
b1010 E
1&
#510
0$
07
0>
b0 ?
b0 <
b0 A
0&
#520
b1 F
1&
#530
b1 A
0&
#540
b10 F
1&
#550
b10 A
0&
#560
b11 F
1&
#570
b11 A
0&
#580
b100 F
1&
#590
17
b100 A
0&
#600
x$
b101 F
1&
#610
0$
b1 <
0&
#620
x$
b110 F
1&
#630
0$
b10 <
0&
#640
x$
b111 F
1&
#650
0$
b11 <
0&
#660
x$
b1000 F
1&
#670
0$
b100 <
0&
#680
x$
b1001 F
1&
#690
0$
b101 <
0&
#700
x$
b1010 F
1&
#710
0$
b110 <
0&
#720
x$
b1011 F
1&
#730
0$
b111 <
0&
#740
x$
b1100 F
1&
#750
0$
07
b1 ?
b0 A
b0 <
0&
#760
b1101 F
1&
#770
b1 A
0&
#780
b1110 F
1&
#790
b10 A
0&
#800
1;
b0 G
b10111 ,
b10111 0
b1111 F
1&
#810
1>
0&
#820
b1 G
1&
#830
b11 A
0&
#840
b10 G
1&
#850
17
b100 A
0&
#860
x$
b11 G
1&
#870
0$
b1 <
0&
#880
x$
b100 G
1&
#890
0$
b10 <
0&
#900
x$
b101 G
1&
#910
0$
b11 <
0&
#920
x$
b110 G
1&
#930
0$
b100 <
0&
#940
x$
b111 G
1&
#950
0$
b101 <
0&
#960
x$
b1000 G
1&
#970
0$
b110 <
0&
#980
x$
b1001 G
1&
#990
0$
b111 <
0&
#1000
07
b1xxxxxxxxx %
b1xxxxxxxxx 5
0>
b0 ?
b0 <
b0 A
0;
b1010 :
b0 H
b10100 ,
b10100 0
b1010 G
0&
#1020
b1 H
1&
#1030
b1 A
0&
#1040
b10 H
1&
#1050
b10 A
0&
#1060
b11 H
1&
#1070
b11 A
0&
#1080
b100 H
1&
#1090
17
b100 A
0&
#1100
x$
b101 H
1&
